MANIFEST.in
README.txt
setup.cfg
setup.py
pyldr/CustomizeDemand.py
pyldr/DR.py
pyldr/Input.py
pyldr/LDR.py
pyldr/MSSP.py
pyldr/NETWORK.py
pyldr/SIM.py
pyldr/SIM_ALP.py
pyldr/SIM_Resolve_First.py
pyldr/SIM_Resolve_Second.py
pyldr/__init__.py
pyldr/algs.py
pyldr/alter_solve.py
pyldr/example1.py
pyldr/inter.py
pyldr/linear.py
pyldr/mabinter.py
pyldr/main.py
pyldr/opt_tri_linear.py
pyldr/piecewise_linear.py
pyldr/processer.py
pyldr/rALP.py
pyldr/script.py
pyldr/setup.py
pyldr/test_alter.py
pyldr/test_plot.py
pyldr/tri_linear.py
pyldr.egg-info/PKG-INFO
pyldr.egg-info/SOURCES.txt
pyldr.egg-info/dependency_links.txt
pyldr.egg-info/requires.txt
pyldr.egg-info/top_level.txt