Metadata-Version: 1.0
Name: pyldr
Version: 0.1.2
Summary: Python Package for Linear Decision Rule and Generalized Decision Rule
Home-page: UNKNOWN
Author: Zhan Lin
Author-email: dy403164418@gmail.com
License: MIT License
Platform: UNKNOWN
